pyferno/__init__.py
pyferno/exception.py
pyferno/promise.py
pyferno/tests/__init__.py
pyferno/tests/unit/__init__.py
pyferno/tests/unit/test_promise.py
pyferno/version.py
pyferno-1.5.2.dist-info/LICENSE
pyferno-1.5.2.dist-info/WHEEL
pyferno-1.5.2.dist-info/METADATA
pyferno-1.5.2.dist-info/RECORD
