Metadata-Version: 2.1
Name: pyferno
Version: 1.5.2
Summary: PyFerno - the async/promise library for running Python 3 async tasks
Home-page: https://github.com/svenvarkel/pyferno
License: MIT
Author: Sven Varkel
Author-email: sven@prototypely.com
Requires-Python: >=3.7
Classifier: License :: OSI Approved :: MIT License
Classifier: Operating System :: OS Independent
Classifier: Programming Language :: Python :: 3
Classifier: Programming Language :: Python :: 3.7
Classifier: Programming Language :: Python :: 3.8
Classifier: Programming Language :: Python :: 3.9
Classifier: Programming Language :: Python :: 3.10
Classifier: Programming Language :: Python :: 3.11
Classifier: Programming Language :: Python :: 3
Requires-Dist: tqdm (>=4.62.3,<5.0.0)
Project-URL: Repository, https://github.com/svenvarkel/pyferno
